LICENSE.txt
MANIFEST.in
README.md
setup.cfg
setup.py
nyumytimecli/__init__.py
nyumytimecli/browser.py
nyumytimecli/config.ini
nyumytimecli/helper.py
nyumytimecli/nyumytimecli.py
nyumytimecli.egg-info/PKG-INFO
nyumytimecli.egg-info/SOURCES.txt
nyumytimecli.egg-info/dependency_links.txt
nyumytimecli.egg-info/entry_points.txt
nyumytimecli.egg-info/requires.txt
nyumytimecli.egg-info/top_level.txt
tests/.DS_Store
tests/test_browser.py
tests/test_helper.py
tests/test_nyumytimecli.py
tests/test_html/test_iframe_page.html
tests/test_html/test_status_page.html
tests/test_html/test_while_find.html