Metadata-Version: 2.1
Name: nyumytimecli
Version: 0.0.5
Summary: A command-line interface for NYU's employee time-tracking website
Home-page: https://github.com/matteosandrin/nyu-mytime-cli
Author: Matteo Sandrin
License: UNKNOWN
Platform: UNKNOWN
